republic_prompt/__init__.py
republic_prompt/core.py
republic_prompt/exception.py
republic_prompt/loader.py
republic_prompt/renderer.py
republic_prompt/loaders/__init__.py
republic_prompt/loaders/base.py
republic_prompt/loaders/python.py
republic_prompt-0.1.0.dist-info/METADATA
republic_prompt-0.1.0.dist-info/WHEEL
republic_prompt-0.1.0.dist-info/RECORD
