Metadata-Version: 2.4
Name: republic-prompt
Version: 0.1.0
Summary: Manage your prompts as recipes - lightweight and modern.
Author-email: Chojan Shang <psiace@apache.org>
Requires-Python: >=3.11
Requires-Dist: jinja2>=3.1.0
Requires-Dist: pydantic>=2.0.0
Requires-Dist: toml>=0.10.0
Provides-Extra: dev
Requires-Dist: pytest>=8.0.0; extra == 'dev'
Requires-Dist: ruff>=0.8.0; extra == 'dev'
